ddestiny_django_pagination-2.1.1.dist-info/DESCRIPTION.rst
ddestiny_django_pagination-2.1.1.dist-info/METADATA
ddestiny_django_pagination-2.1.1.dist-info/RECORD
ddestiny_django_pagination-2.1.1.dist-info/WHEEL
ddestiny_django_pagination-2.1.1.dist-info/metadata.json
ddestiny_django_pagination-2.1.1.dist-info/top_level.txt
linaro_django_pagination/__init__.py
linaro_django_pagination/middleware.py
linaro_django_pagination/models.py
linaro_django_pagination/paginator.py
linaro_django_pagination/settings.py
linaro_django_pagination/tests.py
linaro_django_pagination/locale/de/LC_MESSAGES/django.po
linaro_django_pagination/locale/es/LC_MESSAGES/django.po
linaro_django_pagination/locale/fi/LC_MESSAGES/django.po
linaro_django_pagination/locale/fr/LC_MESSAGES/django.po
linaro_django_pagination/locale/it/LC_MESSAGES/django.po
linaro_django_pagination/locale/nn/LC_MESSAGES/django.po
linaro_django_pagination/locale/no/LC_MESSAGES/django.po
linaro_django_pagination/locale/pl/LC_MESSAGES/django.po
linaro_django_pagination/locale/pt/LC_MESSAGES/django.po
linaro_django_pagination/locale/pt_BR/LC_MESSAGES/django.po
linaro_django_pagination/locale/ru/LC_MESSAGES/django.po
linaro_django_pagination/locale/tr/LC_MESSAGES/django.po
linaro_django_pagination/templates/pagination/pagination.html
linaro_django_pagination/templatetags/__init__.py
linaro_django_pagination/templatetags/pagination_tags.py
linaro_django_pagination/test_project/__init__.py
linaro_django_pagination/test_project/manage.py
linaro_django_pagination/test_project/settings.py
linaro_django_pagination/test_project/tests.py
linaro_django_pagination/test_project/urls.py
linaro_django_pagination/test_project/example/__init__.py
linaro_django_pagination/test_project/example/models.py
linaro_django_pagination/test_project/example/urls.py
linaro_django_pagination/test_project/example/views.py
linaro_django_pagination/test_project/example/templates/example/list.html
linaro_django_pagination/test_project/example/templates/example/two_lists.html
linaro_django_pagination/test_project/example/templates/pagination/custom_pagination.html
linaro_django_pagination_backup/__init__.py
linaro_django_pagination_backup/middleware.py
linaro_django_pagination_backup/models.py
linaro_django_pagination_backup/paginator.py
