Metadata-Version: 2.0
Name: ddestiny-django-pagination
Version: 2.1.1
Summary: linaro-django-pagination fork
Home-page: https://github.com/zyga/django-pagination
Author: Zygmunt Krynicki
Author-email: zygmunt.krynicki@linaro.org
License: BSD
Keywords: pagination,django
Platform: UNKNOWN
Classifier: Development Status :: 4 - Beta
Classifier: Environment :: Web Environment
Classifier: Framework :: Django
Classifier: Intended Audience :: Developers
Classifier: License :: OSI Approved :: BSD License
Classifier: Operating System :: OS Independent
Classifier: Programming Language :: Python :: 2.6
Classifier: Programming Language :: Python :: 2.7
Classifier: Programming Language :: Python :: 3
Classifier: Programming Language :: Python :: 3.3
Requires-Dist: django (>=1.2)
